reporover/__init__.py
reporover/actions.py
reporover/constants.py
reporover/main.py
reporover/pullrequest.py
reporover/repository.py
reporover/status.py
reporover/user.py
reporover/util.py
reporover-0.1.2.dist-info/METADATA
reporover-0.1.2.dist-info/WHEEL
reporover-0.1.2.dist-info/entry_points.txt
reporover-0.1.2.dist-info/RECORD
