Metadata-Version: 2.4
Name: reporover
Version: 0.1.2
Summary: RepoRover manages and analyzes remote GitHub repositories! Arf!
Author-email: "Gregory M. Kapfhammer" <gkapfham@allegheny.edu>
Keywords: git,github
Classifier: Environment :: Console
Classifier: Intended Audience :: Developers
Classifier: Operating System :: OS Independent
Classifier: Programming Language :: Python :: 3 :: Only
Classifier: Programming Language :: Python :: 3.11
Classifier: Programming Language :: Python :: 3.12
Classifier: Programming Language :: Python :: 3.13
Classifier: Topic :: Software Development :: Quality Assurance
Classifier: Topic :: Software Development :: Testing
Requires-Python: >=3.11
Requires-Dist: gitpython>=3.1.44
Requires-Dist: requests>=2.32.3
Requires-Dist: rich>=13.9.4
Requires-Dist: typer>=0.15.1
